MCM3000/MCM3000.py
MCM3000/__init__.py
MCM3000-0.2.dist-info/LICENSE
MCM3000-0.2.dist-info/METADATA
MCM3000-0.2.dist-info/WHEEL
MCM3000-0.2.dist-info/top_level.txt
MCM3000-0.2.dist-info/RECORD
