Metadata-Version: 2.1
Name: MCM3000
Version: 0.2
Summary: Python serial interface for Thorlabs MCM3000 Series 3-Axis Controller originally forked from amsikking/thorlabs_MCM3000.
Home-page: UNKNOWN
Author: sstucker
Author-email: sstucker@nyu.edu
License: UNKNOWN
Platform: UNKNOWN
Classifier: Programming Language :: Python :: 3
Classifier: License :: OSI Approved :: GNU General Public License v3 (GPLv3)
Classifier: Operating System :: OS Independent
Requires-Python: >=3.6
